{
  "LOAD": "تحميل",
  "LAUNCHING": "جاري التشغيل",
  "Loading...": "جاري التحميل...",
  "Save": "حفظ",
  "Cancel": "إلغاء",
  "Delete": "حذف",
  "Edit": "تعديل",
  "Add": "إضافة",
  "Remove": "إزالة",
  "Clear": "مسح",
  "Search": "بحث",
  "Filter": "تصفية",
  "Sort": "ترتيب",
  "Export": "تصدير",
  "Import": "استيراد",
  "Print": "طباعة",
  "Download": "تنزيل",
  "Upload": "رفع",
  "Zoom In": "تكبير",
  "Zoom Out": "تصغير",
  "Pan": "تحريك",
  "Rotate": "دوران",
  "Flip Horizontal": "قلب أفقي",
  "Flip Vertical": "قلب عمودي",
  "Reset View": "إعادة ضبط العرض",
  "Invert": "عكس",
  "Brightness": "السطوع",
  "Contrast": "التباين",
  "Measurements": "القياسات",
  "Length": "الطول",
  "Area": "المساحة",
  "Angle": "الزاوية",
  "Rectangle": "مستطيل",
  "Ellipse": "قطع ناقص",
  "Point": "نقطة",
  "Arrow": "سهم",
  "Freehand": "رسم حر",
  "Magnify": "تكبير",
  "Window Level": "مستوى النافذة",
  "Patient Name": "اسم المريض",
  "Patient ID": "رقم المريض",
  "Study Date": "تاريخ الدراسة",
  "Study Description": "وصف الدراسة",
  "Series Description": "وصف السلسلة",
  "Modality": "نوع الفحص",
  "Body Part": "جزء الجسم",
  "Institution": "المؤسسة",
  "Referring Physician": "الطبيب المحيل",
  "AI Analysis": "التحليل الذكي",
  "Auto Measure": "قياس تلقائي",
  "Report": "تقرير",
  "Generate Report": "إنشاء تقرير",
  "Previous Image": "الصورة السابقة",
  "Next Image": "الصورة التالية",
  "Play Cine": "تشغيل السينما",
  "Stop Cine": "إيقاف السينما",
  "Layout": "التخطيط",
  "Crosshairs": "علامات التقاطع",
  "Reference Lines": "خطوط المرجع",
  "Stack Scroll": "التمرير المكدس",
  "More Tools": "أدوات إضافية",
  "Preferences": "التفضيلات",
  "About": "حول",
  "Help": "مساعدة",
  "Logout": "تسجيل خروج",
  "BrainSAIT Medical Imaging": "BrainSAIT للصور الطبية",
  "Powered by AI": "مدعوم بالذكاء الاصطناعي",
  "Loading studies...": "جاري تحميل الدراسات...",
  "No studies found": "لم يتم العثور على دراسات",
  "Error loading study": "خطأ في تحميل الدراسة",
  "Series": "السلسلة",
  "Images": "الصور",
  "Instance": "النسخة"
}
